elasticsearch_follow/__init__.py
elasticsearch_follow/_version.py
elasticsearch_follow/cli.py
elasticsearch_follow/default_processor.py
elasticsearch_follow/elasticsearch_fetch.py
elasticsearch_follow/elasticsearch_follow.py
elasticsearch_follow/entry_tracker.py
elasticsearch_follow/follower.py
elasticsearch_follow/formatting_processor.py
elasticsearch_follow-0.2.6.dist-info/LICENSE
elasticsearch_follow-0.2.6.dist-info/METADATA
elasticsearch_follow-0.2.6.dist-info/WHEEL
elasticsearch_follow-0.2.6.dist-info/entry_points.txt
elasticsearch_follow-0.2.6.dist-info/top_level.txt
elasticsearch_follow-0.2.6.dist-info/RECORD
