Metadata-Version: 2.1
Name: elasticsearch-follow
Version: 0.2.6
Summary: An Elasticsearch tail
Home-page: https://github.com/mdreem/elasticsearch_follow
Author: Marc Schiereck
Author-email: mdreem@fastmail.fm
License: UNKNOWN
Platform: UNKNOWN
Classifier: Operating System :: OS Independent
Classifier: License :: OSI Approved :: MIT License
Classifier: Programming Language :: Python :: 3
Requires-Dist: python-dateutil
Requires-Dist: elasticsearch
Requires-Dist: pytz
Requires-Dist: click
Requires-Dist: certifi
